{
  "main": {
    "id": "723fe0d093fd254f",
    "type": "split",
    "children": [
      {
        "id": "9fe59e0920929e7a",
        "type": "tabs",
        "children": [
          {
            "id": "0707dfc5ad5bfbaf",
            "type": "leaf",
            "state": {
              "type": "image",
              "state": {
                "file": "public/preview.png"
              },
              "icon": "lucide-image",
              "title": "preview"
            }
          }
        ]
      }
    ],
    "direction": "vertical"
  },
  "left": {
    "id": "b4668f055ea4457c",
    "type": "split",
    "children": [
      {
        "id": "34e48e269605cbc5",
        "type": "tabs",
        "children": [
          {
            "id": "44aa57b16892837e",
            "type": "leaf",
            "state": {
              "type": "file-explorer",
              "state": {
                "sortOrder": "alphabetical",
                "autoReveal": false
              },
              "icon": "lucide-folder-closed",
              "title": "Files"
            }
          },
          {
            "id": "db6f76b293f0cd73",
            "type": "leaf",
            "state": {
              "type": "search",
              "state": {
                "query": "",
                "matchingCase": false,
                "explainSearch": false,
                "collapseAll": false,
                "extraContext": false,
                "sortOrder": "alphabetical"
              },
              "icon": "lucide-search",
              "title": "Search"
            }
          },
          {
            "id": "36575cc2e66ddd35",
            "type": "leaf",
            "state": {
              "type": "bookmarks",
              "state": {},
              "icon": "lucide-bookmark",
              "title": "Bookmarks"
            }
          }
        ]
      }
    ],
    "direction": "horizontal",
    "width": 300
  },
  "right": {
    "id": "a5bb0d6bd3b0c876",
    "type": "split",
    "children": [
      {
        "id": "3abe9236744030e3",
        "type": "tabs",
        "children": [
          {
            "id": "335c3fc69be3d40d",
            "type": "leaf",
            "state": {
              "type": "backlink",
              "state": {
                "file": "posts/How to increase linux swap/post.md",
                "collapseAll": false,
                "extraContext": false,
                "sortOrder": "alphabetical",
                "showSearch": false,
                "searchQuery": "",
                "backlinkCollapsed": false,
                "unlinkedCollapsed": true
              },
              "icon": "links-coming-in",
              "title": "Backlinks for post"
            }
          },
          {
            "id": "0c30fcd91b78f006",
            "type": "leaf",
            "state": {
              "type": "outgoing-link",
              "state": {
                "file": "posts/How to increase linux swap/post.md",
                "linksCollapsed": false,
                "unlinkedCollapsed": true
              },
              "icon": "links-going-out",
              "title": "Outgoing links from post"
            }
          },
          {
            "id": "55e35e0603f7ab3c",
            "type": "leaf",
            "state": {
              "type": "tag",
              "state": {
                "sortOrder": "frequency",
                "useHierarchy": true,
                "showSearch": false,
                "searchQuery": ""
              },
              "icon": "lucide-tags",
              "title": "Tags"
            }
          },
          {
            "id": "d8ba7fd22cd14fb0",
            "type": "leaf",
            "state": {
              "type": "outline",
              "state": {
                "file": "posts/How to increase linux swap/post.md",
                "followCursor": false,
                "showSearch": false,
                "searchQuery": ""
              },
              "icon": "lucide-list",
              "title": "Outline of post"
            }
          },
          {
            "id": "2a5479f2ffa5d4a7",
            "type": "leaf",
            "state": {
              "type": "git-view",
              "state": {},
              "icon": "git-pull-request",
              "title": "Source Control"
            }
          }
        ],
        "currentTab": 4
      }
    ],
    "direction": "horizontal",
    "width": 300
  },
  "left-ribbon": {
    "hiddenItems": {
      "switcher:Open quick switcher": false,
      "graph:Open graph view": false,
      "canvas:Create new canvas": false,
      "daily-notes:Open today's daily note": false,
      "templates:Insert template": false,
      "command-palette:Open command palette": false,
      "obsidian-git:Open Git source control": false
    }
  },
  "active": "0707dfc5ad5bfbaf",
  "lastOpenFiles": [
    "vite.config.ts.timestamp-1739595183732-ec28e9aafd7e7.mjs",
    "vite.config.ts.timestamp-1739595183676-69a3ac073626.mjs",
    "vite.config.ts.timestamp-1739595116458-3c59110849cfb.mjs",
    "vite.config.ts.timestamp-1739595116405-5b8d792bdd9e2.mjs",
    "public/input.png",
    "public/preview.png.png",
    "public/preview.png",
    "vite.config.ts.timestamp-1739594388394-515d32a2f5d02.mjs",
    "vite.config.ts.timestamp-1739594388340-a71c8e97a6197.mjs",
    "public/Untitled.md",
    "README.md",
    "vite.config.ts.timestamp-1739594184964-e2ce26b45fa99.mjs",
    "vite.config.ts.timestamp-1739594184911-fd036d5d281b9.mjs",
    "vite.config.ts.timestamp-1739594167745-7da8e07ee48f2.mjs",
    "preview",
    "prev",
    "node_modules/wrap-ansi/node_modules/string-width/readme.md",
    "node_modules/@isaacs/cliui/node_modules/string-width/readme.md",
    "node_modules/tslib/SECURITY.md",
    "node_modules/tslib/README.md",
    "node_modules/sprintf-js/README.md",
    "node_modules/sprintf-js/CONTRIBUTORS.md",
    "node_modules/jsbn/CHANGELOG.md",
    "node_modules/jsbn/README.md",
    "node_modules/esprima/README.md",
    "node_modules/escodegen/node_modules/source-map/README.md",
    "node_modules/escodegen/node_modules/source-map/CHANGELOG.md",
    "node_modules/escodegen/README.md",
    "node_modules/ast-types/README.md",
    "node_modules/smart-buffer/docs/ROADMAP.md",
    "node_modules/smart-buffer/docs/README_v3.md",
    "node_modules/smart-buffer/docs/CHANGELOG.md",
    "node_modules/smart-buffer/README.md",
    "node_modules/ip-address/README.md",
    "node_modules/netmask/README.md",
    "node_modules/netmask/CREDITS.md",
    "node_modules/netmask/CHANGELOG.md",
    "node_modules/degenerator/README.md",
    "node_modules/basic-ftp/README.md",
    "public/favicon.png",
    "public/164dcdfe0aeb412993425302c7b0f379.png",
    "node_modules/onnx-proto/node_modules/protobufjs/cli/node_modules/jsdoc/templates/default/static/fonts/OpenSans-Regular-webfont.svg",
    "node_modules/onnx-proto/node_modules/protobufjs/cli/node_modules/jsdoc/templates/default/static/fonts/OpenSans-LightItalic-webfont.svg",
    "node_modules/onnx-proto/node_modules/protobufjs/cli/node_modules/jsdoc/templates/default/static/fonts/OpenSans-Light-webfont.svg",
    "node_modules/onnx-proto/node_modules/protobufjs/cli/node_modules/jsdoc/templates/default/static/fonts/OpenSans-Italic-webfont.svg",
    "node_modules/onnx-proto/node_modules/protobufjs/cli/node_modules/jsdoc/templates/default/static/fonts/OpenSans-BoldItalic-webfont.svg"
  ]
}